{
  "category": [
    {
      "id": "1",
      "title": "Роли",
      "img": "https://firebasestorage.googleapis.com/v0/b/mono-project-35634.appspot.com/o/images%2Fnav-img-rolls.svg?alt=media&token=be67beb4-78f2-48e3-979c-cd673e7a4085",
      "path": "roli"
    },
    {
      "id": "2",
      "title": "Сети",
      "img": "https://firebasestorage.googleapis.com/v0/b/mono-project-35634.appspot.com/o/images%2Fnav-img-sets.svg?alt=media&token=99d81ed8-d74d-45bf-9559-15a4235d2a9e",
      "path": "setu"
    },
    {
      "id": "3",
      "title": "Напої",
      "img": "https://firebasestorage.googleapis.com/v0/b/mono-project-35634.appspot.com/o/images%2Fnav-img-drinks.svg?alt=media&token=83780a9d-4ce2-4423-b221-9a0e97115bf4",
      "path": "beverage"
    },
    {
      "id": "4",
      "title": "Соуси",
      "img": "https://firebasestorage.googleapis.com/v0/b/mono-project-35634.appspot.com/o/images%2Ficon.svg?alt=media&token=72976e0f-587d-48fb-886d-278255fbf34f",
      "path": "souse"
    }
  ],
  "actions": [
    {
      "id": "1",
      "title": "Рол тижня",
      "path": "rus-kozhen-pyatyj-v-podarunok",
      "main_title": "50% знижки на `Рол тижня`",
      "description": "Щотижня діє знижка 50% на один з ролів у нашому меню.“Рол тижня” ви можете знайти на головній сторінці нашого сайту.Знижка діє при мінімальній сумі замовлення 300 грн.Ця акція не поєднується з іншими акціями",
      "image": "https://firebasestorage.googleapis.com/v0/b/mono-project-35634.appspot.com/o/images%2Fimgonline-com-ua-compressed-ryna9n84oqh1-scaled-697x379.jpg?alt=media&token=f0b2bccc-bcc4-4391-9179-d4c85182de90"
    },
    {
      "id": "2",
      "title": "3+1=5",
      "path": "kozhen-pyatyj-rol-v-podarunok",
      "main_title": "`3+1=5`",
      "image": "https://firebasestorage.googleapis.com/v0/b/mono-project-35634.appspot.com/o/images%2Fimgonline-com-ua-compressed-ajbic74qfau00-scaled-697x379.jpg?alt=media&token=733320e3-e0c0-4872-9e63-6552042fef36",
      "description": "Замовляйте 5 ролів, а платіть за 4. Замовляйте 10 ролів, а платіть за 8 і так далі.Безкоштовним вважається рол з найменшою вартістю.Ця акція не поєднується з іншими акціями"
    },
    {
      "id": "3",
      "title": "День народження з Моносуші",
      "path": "samovyviz",
      "main_title": "День народження з Моносуші",
      "description": "Замовте суші на 750 грн та більше. Це можуть бути будь-які позиції з нашого меню.Вкажіть промокод “ДЕНЬ НАРОДЖЕННЯ” під час оформлення замовлення. Покажіть кур’єру при отриманні  документ (оригінал), який підтверджує вашу дату народження.Суші акція діє на ваш  день народження + один день до та після свята.Зверніть увагу: ця акція не сумується з іншими акціями",
      "image": "https://firebasestorage.googleapis.com/v0/b/mono-project-35634.appspot.com/o/images%2Fden-nar-scaled-697x379.jpg?alt=media&token=1a6fa4a3-404a-4202-ac03-9c26d1d76b68"
    },
    {
      "id": "4",
      "title": "Фотомарафон",
      "path": "fotomarafon",
      "main_title": "Фотомарафон",
      "description": "Розіграш проводиться в соціальній мережі Instagram.Щоб стати учасником розіграшу варто зробити будь-який контент на задану тему з нашими ролами.Обов’язково позначай нас на пості або сторі, щоб стати учасником марафону.Переможці визначаються два рази на місяць.Деталі актуального марафону уточнюйте в нашому Instagram: @monosushi",
      "image": "https://firebasestorage.googleapis.com/v0/b/mono-project-35634.appspot.com/o/images%2Fimgonline-com-ua-compressed-tn6e51pounmi-scaled-697x379.jpg?alt=media&token=c8e468d6-225f-4e78-abf2-b8c2c9481103"
    }
  ],
  "products": [
    {
      "id": "1530",
      "category": "Напої",
      "name": "Pepsi",
      "path": "coca-cola",
      "description": "",
      "weight": 0.33,
      "price": 35,
      "imagePath": "C:\\fakepath\\pepsicola.jpg",
      "count": 1,
      "img": "https://firebasestorage.googleapis.com/v0/b/mono-project-35634.appspot.com/o/images%2Fpepsicola.jpg?alt=media&token=099a7ec9-6c8e-47d0-96cc-c5af6338b0bb"
    },
    {
      "id": "946c",
      "category": "Напої",
      "name": "Fanta апельсин",
      "path": "sik-apelsyn",
      "description": "",
      "weight": 0.33,
      "price": 31,
      "imagePath": "C:\\fakepath\\fanta-033.jpg",
      "count": 1,
      "img": "https://firebasestorage.googleapis.com/v0/b/mono-project-35634.appspot.com/o/images%2Ffanta-033.jpg?alt=media&token=7b3d5e7f-caf4-4856-87b8-215fa30aff89"
    },
    {
      "id": "eb6e",
      "category": "Напої",
      "name": "Сік мультивітамін “Sandora”",
      "path": "sik-multyfruktovyj-galicia-1-l",
      "description": null,
      "weight": 1,
      "price": 75,
      "imagePath": "C:\\fakepath\\sandora-multyvitamin.png",
      "count": 1,
      "img": "https://firebasestorage.googleapis.com/v0/b/mono-project-35634.appspot.com/o/images%2Fsandora-multyvitamin.png?alt=media&token=1fd74402-13a8-43cc-adfc-c76a4a709be9"
    },
    {
      "id": "dce7",
      "category": "Напої",
      "name": "Сік вишневий “Sandora”",
      "path": "sik-yabluchno-vyshnevyj-galicia-1-l",
      "description": "",
      "weight": 1,
      "price": 75,
      "imagePath": "C:\\fakepath\\sandora-vyshnevyj.png",
      "count": 1,
      "img": "https://firebasestorage.googleapis.com/v0/b/mono-project-35634.appspot.com/o/images%2Fsandora-vyshnevyj.png?alt=media&token=140de1bc-0299-472a-ac9d-42114d81db3a"
    },
    {
      "id": "becf",
      "category": "Напої",
      "name": "Сік апельсиновий “Sandora”",
      "path": "product/sik-yabluchnyj-galicia",
      "description": null,
      "weight": 1,
      "price": 75,
      "imagePath": "C:\\fakepath\\sandora-apelsyn.png",
      "count": 1,
      "img": "https://firebasestorage.googleapis.com/v0/b/mono-project-35634.appspot.com/o/images%2Fsandora-apelsyn.png?alt=media&token=9e60ba0c-00cf-4611-888f-5a75a15d4084"
    },
    {
      "id": "f252",
      "category": "Соуси",
      "name": "Імбир",
      "path": "imbyr",
      "description": "",
      "weight": 30,
      "price": 15,
      "imagePath": "C:\\fakepath\\3333.png",
      "count": 1,
      "img": "https://firebasestorage.googleapis.com/v0/b/mono-project-35634.appspot.com/o/images%2F3333.png?alt=media&token=3c73934a-96ec-4827-b320-45d066a8b146"
    },
    {
      "id": "341c",
      "category": "Соуси",
      "name": "Васабі",
      "path": "vasabi",
      "description": "",
      "weight": 25,
      "price": 15,
      "imagePath": "C:\\fakepath\\4444.png",
      "count": 1,
      "img": "https://firebasestorage.googleapis.com/v0/b/mono-project-35634.appspot.com/o/images%2F4444.png?alt=media&token=0ac105aa-48a3-45b9-9179-3e6df10e58bd"
    },
    {
      "id": "83af",
      "category": "Соуси",
      "name": "Унагі соус",
      "path": "unagi-sous",
      "description": null,
      "weight": 50,
      "price": 34,
      "imagePath": "C:\\fakepath\\66666.jpg",
      "count": 1,
      "img": "https://firebasestorage.googleapis.com/v0/b/mono-project-35634.appspot.com/o/images%2F66666.jpg?alt=media&token=9bf88846-d527-4862-a72d-414dd0071711"
    },
    {
      "id": "b7ba",
      "category": "Соуси",
      "name": "Спайсі соус",
      "path": "kopiyaunagi-sous",
      "description": "",
      "weight": 50,
      "price": 34,
      "imagePath": "C:\\fakepath\\8786612.png",
      "count": 1,
      "img": "https://firebasestorage.googleapis.com/v0/b/mono-project-35634.appspot.com/o/images%2F8786612.png?alt=media&token=c68b09e1-6fb9-456c-a1ac-d51aadbbce8e"
    },
    {
      "id": "b47a",
      "category": "Сети",
      "name": "Сет Філадельфія",
      "path": "product/zapechenyj-set",
      "description": "Філадельфія: з лососем / в кунжуті / з тунцем / з вугрем",
      "weight": 1070,
      "price": 1050,
      "imagePath": "C:\\fakepath\\imgonline-com-ua-compressed-jknw6idh54664-scaled.jpg",
      "count": 1,
      "img": "https://firebasestorage.googleapis.com/v0/b/mono-project-35634.appspot.com/o/images%2Fimgonline-com-ua-compressed-jknw6idh54664-scaled.jpg?alt=media&token=9cf77ec3-e065-4809-8d98-32145570aa1d"
    },
    {
      "id": "0e88",
      "category": "Сети",
      "name": "Запечений сет",
      "path": "zapechenyj-set-2",
      "description": "Запечений сирний з креветкою Запечений моно з лососем",
      "weight": 680,
      "price": 605,
      "imagePath": "C:\\fakepath\\imgonline-com-ua-compressed-wnclohqe80-scaled.jpg",
      "count": 1,
      "img": "https://firebasestorage.googleapis.com/v0/b/mono-project-35634.appspot.com/o/images%2Fimgonline-com-ua-compressed-wnclohqe80-scaled.jpg?alt=media&token=be3f656f-08d8-412a-9b4b-6f8c462d5f31"
    },
    {
      "id": "df14",
      "category": "Сети",
      "name": "Сет Каліфорнія",
      "path": "set-kunzhutnyj",
      "description": "Каліфорнія: з лососем / з креветкою / з крабом / з вугрем",
      "weight": 1000,
      "price": 1050,
      "imagePath": "C:\\fakepath\\kaliforniya-scaled.jpg",
      "count": 1,
      "img": "https://firebasestorage.googleapis.com/v0/b/mono-project-35634.appspot.com/o/images%2Fkaliforniya-scaled.jpg?alt=media&token=61e78a1c-2dff-4b89-a91f-58edddcd9b4d"
    },
    {
      "id": "069b",
      "category": "Сети",
      "name": "Класичний сет",
      "path": "klasychnyj-set",
      "description": "Філадельфія з лососем / Каліфорнія з крабом",
      "weight": 530,
      "price": 510,
      "imagePath": "C:\\fakepath\\imgonline-com-ua-compressed-onqhpofp61f5-scaled.jpg",
      "count": 1,
      "img": "https://firebasestorage.googleapis.com/v0/b/mono-project-35634.appspot.com/o/images%2Fimgonline-com-ua-compressed-onqhpofp61f5-scaled.jpg?alt=media&token=5c96e6ff-5fb0-4921-8ba6-46792f48846e"
    },
    {
      "id": "3c70",
      "category": "Сети",
      "name": "Сет Макі",
      "path": "set-maki",
      "description": " Макі: з авокадо / з лососем / з огірком / з вугрем",
      "weight": 480,
      "price": 650,
      "imagePath": "C:\\fakepath\\imgonline-com-ua-compressed-iomk776oplygk9-scaled.jpg",
      "count": 1,
      "img": "https://firebasestorage.googleapis.com/v0/b/mono-project-35634.appspot.com/o/images%2Fimgonline-com-ua-compressed-iomk776oplygk9-scaled.jpg?alt=media&token=369ebf88-3007-4ab0-bfb1-8dc96fbb6022"
    },
    {
      "id": "c856",
      "category": "Сети",
      "name": "Унагі сет",
      "path": "unagi-set",
      "description": "Філадельфія з вугрем / Каліфорнія з вугрем / Фелікс з вугрем",
      "weight": 800,
      "price": 945,
      "imagePath": "C:\\fakepath\\imgonline-com-ua-compressed-gqugtbdvryaongv-scaled.jpg",
      "count": 1,
      "img": "https://firebasestorage.googleapis.com/v0/b/mono-project-35634.appspot.com/o/images%2Fimgonline-com-ua-compressed-gqugtbdvryaongv-scaled.jpg?alt=media&token=35be885a-50cd-44db-9027-3f05de0294a2"
    },
    {
      "id": "8ab7",
      "category": "Роли",
      "name": "Філадельфія з лососем",
      "path": "filadelfiya-z-lososem",
      "description": "Риc, крем сир, огірок, лосось",
      "weight": 280,
      "price": 287,
      "imagePath": "C:\\fakepath\\1.-filadelfiya-z-lososem.jpg",
      "count": 1,
      "img": "https://firebasestorage.googleapis.com/v0/b/mono-project-35634.appspot.com/o/images%2F1.-filadelfiya-z-lososem.jpg?alt=media&token=8cf6ee70-47d9-4687-8c4a-f58e154a7635"
    },
    {
      "id": "41d8",
      "category": "Роли",
      "name": "Філадельфія в кунжуті",
      "path": "filadelfiya-v-kunzhuti",
      "description": "Рис, крем сир, огірок, лосось, кунжут",
      "weight": 240,
      "price": 268,
      "imagePath": "C:\\fakepath\\2.-filadelfiya-v-kunzhuti.jpg",
      "count": 1,
      "img": "https://firebasestorage.googleapis.com/v0/b/mono-project-35634.appspot.com/o/images%2F2.-filadelfiya-v-kunzhuti.jpg?alt=media&token=cdf4d791-cacf-4f6f-bcc9-21981142b852"
    },
    {
      "id": "4c52",
      "category": "Роли",
      "name": "Філадельфія з тунцем",
      "path": "filadelfiya-z-tunczem",
      "description": "Риc, крем сир, авокадо, тунець, cоус солодкий чилі",
      "weight": 270,
      "price": 322,
      "imagePath": "C:\\fakepath\\photo_2022-07-09_13-28-56.jpg",
      "count": 1,
      "img": "https://firebasestorage.googleapis.com/v0/b/mono-project-35634.appspot.com/o/images%2Fphoto_2022-07-09_13-28-56.jpg?alt=media&token=94c2483b-6879-4fee-9061-f43a44b4672e"
    },
    {
      "id": "3ef8",
      "category": "Роли",
      "name": "Фелікс з лососем – 50%",
      "path": "feliks-z-lososem-50",
      "description": "Рис, крем сир, авокадо, салат айсберг, кунжут, лосось, спайсі соус",
      "weight": 300,
      "price": 161,
      "imagePath": "C:\\fakepath\\5.-feliks-z-lososem.jpg",
      "count": 1,
      "img": "https://firebasestorage.googleapis.com/v0/b/mono-project-35634.appspot.com/o/images%2F5.-feliks-z-lososem.jpg?alt=media&token=1aea58c9-0dd7-4955-a215-53fa045d48c4"
    },
    {
      "id": "5f8a",
      "category": "Роли",
      "name": "Філадельфія з вугрем",
      "path": "filadelfiya-z-vugrem",
      "description": "Рис, крем сир, авокадо, вугор, унагі соус, кунжут",
      "weight": 280,
      "price": 359,
      "imagePath": "C:\\fakepath\\4.-filadelfiya-z-vugr.jpg",
      "count": 1,
      "img": "https://firebasestorage.googleapis.com/v0/b/mono-project-35634.appspot.com/o/images%2F4.-filadelfiya-z-vugr.jpg?alt=media&token=c86b02d1-1786-4fa1-91ff-b1e14b9c59c9"
    },
    {
      "id": "4204",
      "category": "Роли",
      "name": "Філадельфія з креветкою",
      "path": "filadelfiya-z-krevetkoyu",
      "description": "Рис, крем сир, огірок, креветка, лосось",
      "weight": 280,
      "price": 327,
      "imagePath": "C:\\fakepath\\5.-filadelfiya-z-krevetkoyu.jpg",
      "count": 1,
      "img": "https://firebasestorage.googleapis.com/v0/b/mono-project-35634.appspot.com/o/images%2F5.-filadelfiya-z-krevetkoyu.jpg?alt=media&token=16e57c4e-7ce9-455e-8603-731616e059a1"
    },
    {
      "id": "7f3d",
      "category": "Роли",
      "name": "Філадельфія грін з креветкою",
      "path": "filadelfiya-grin-z-krevetkoyu",
      "description": "Рис, крем сир, огірок, креветка, авокадо, спайсі соус, унагі соус",
      "weight": 270,
      "price": 319,
      "imagePath": "C:\\fakepath\\7.-filadelfiya-grin-z-krevetkoyu.jpg",
      "count": 1,
      "img": "https://firebasestorage.googleapis.com/v0/b/mono-project-35634.appspot.com/o/images%2F7.-filadelfiya-grin-z-krevetkoyu.jpg?alt=media&token=3751c377-03a7-4028-8efc-dc2fad1cc86b"
    },
    {
      "id": "8b6d",
      "category": "Роли",
      "name": "Каліфорнія з крабом",
      "path": "kaliforniya-z-krabom",
      "description": "Рис, спайсі соус, авокадо, огірок, краб, кунжут",
      "weight": 250,
      "price": 263,
      "imagePath": "C:\\fakepath\\3.1-kaliforniya-z-krabom-v-kunzhuti.jpg",
      "count": 1,
      "img": "https://firebasestorage.googleapis.com/v0/b/mono-project-35634.appspot.com/o/images%2F3.1-kaliforniya-z-krabom-v-kunzhuti.jpg?alt=media&token=1c52ae7a-8d20-43e1-ba76-83aa82371b28"
    },
    {
      "id": "2bee",
      "category": "Роли",
      "name": "Каліфорнія з лососем",
      "path": "kaliforniya-z-lososem-2",
      "description": "Рис, спайсі соус, авокадо, огірок, лосось, кунжут",
      "weight": 250,
      "price": 273,
      "imagePath": "C:\\fakepath\\1.1-kaliforniya-z-lososem-v-kunzhuti.jpg",
      "count": 1,
      "img": "https://firebasestorage.googleapis.com/v0/b/mono-project-35634.appspot.com/o/images%2F1.1-kaliforniya-z-lososem-v-kunzhuti.jpg?alt=media&token=0bcd110c-5cf8-4cd6-956c-7ed9d1ca40cb"
    },
    {
      "id": "8176",
      "category": "Роли",
      "name": "Каліфорнія з креветкою",
      "path": "kaliforniya-z-krevetkoyu",
      "description": "Рис, спайсі соус, авокадо, огірок, креветка, кунжут",
      "weight": 250,
      "price": 283,
      "imagePath": "C:\\fakepath\\2.1-kaliforniya-z-krevetkoyu-v-kunzhuti.jpg",
      "count": 1,
      "img": "https://firebasestorage.googleapis.com/v0/b/mono-project-35634.appspot.com/o/images%2F2.1-kaliforniya-z-krevetkoyu-v-kunzhuti.jpg?alt=media&token=f0ea0d6c-f41f-4856-a1fd-a4124a8880bc"
    },
    {
      "id": "4e02",
      "category": "Роли",
      "name": "Каліфорнія з вугрем",
      "path": "kopiyakaliforniya-z-krevetkoyu",
      "description": "Рис, авокадо, огірок, вугор, чорний кунжут, унагі соус",
      "weight": 240,
      "price": 308,
      "imagePath": "C:\\fakepath\\4.-kaliforniya-z-vugrem.jpg",
      "count": 1,
      "img": "https://firebasestorage.googleapis.com/v0/b/mono-project-35634.appspot.com/o/images%2F4.-kaliforniya-z-vugrem.jpg?alt=media&token=3a61a827-96f2-44ce-82c8-0c5416075728"
    },
    {
      "id": "f661",
      "category": "Роли",
      "name": "Запечений сирний з креветкою",
      "path": "zapechenyj-syrnyj-z-krevetkoyu",
      "description": "Рис, крем сир, салат айсберг, креветка, кунжут, сирний соус, унагі соус",
      "weight": 330,
      "price": 344,
      "imagePath": "C:\\fakepath\\2.-zapechenyj-syrnyj-z-los.jpg",
      "count": 1,
      "img": "https://firebasestorage.googleapis.com/v0/b/mono-project-35634.appspot.com/o/images%2F2.-zapechenyj-syrnyj-z-los.jpg?alt=media&token=bdd8b5fb-4bd0-4dfb-8cff-87ff2fede722"
    },
    {
      "id": "dddc",
      "category": "Роли",
      "name": "Запечений моно з креветкою",
      "path": "zapechenyj-mono-z-krevetkoyu",
      "description": "Рис, крем сир, салат айсберг, креветка, кунжут, моно соус, унагі соус",
      "weight": 330,
      "price": 317,
      "imagePath": "C:\\fakepath\\1.-zapechenyj-mono-z-los (1).jpg",
      "count": 1,
      "img": "https://firebasestorage.googleapis.com/v0/b/mono-project-35634.appspot.com/o/images%2F1.-zapechenyj-mono-z-los%20(1).jpg?alt=media&token=3bce2ac4-be99-4de2-8339-ac452b5f2753"
    },
    {
      "id": "f089",
      "category": "Роли",
      "name": "Запечений сирний з лососем",
      "path": "zapechenyj-syrnyj-z-lososem",
      "description": "Рис, крем сир, салат айсберг, лосось, кунжут, сирний соус, унагі соус",
      "weight": 330,
      "price": 334,
      "imagePath": "C:\\fakepath\\2.-zapechenyj-syrnyj-z-los (1).jpg",
      "count": 1,
      "img": "https://firebasestorage.googleapis.com/v0/b/mono-project-35634.appspot.com/o/images%2F2.-zapechenyj-syrnyj-z-los%20(1).jpg?alt=media&token=591ec4aa-00b8-48fc-90aa-192e80a24cef"
    },
    {
      "id": "71a4",
      "category": "Роли",
      "name": "Запечений моно з лососем",
      "path": "zapechenyj-mono-z-lososem",
      "description": " Рис, крем сир, салат айсберг, лосось, кунжут, моно соус, унагі соус",
      "weight": 330,
      "price": 307,
      "imagePath": "C:\\fakepath\\1.-zapechenyj-mono-z-los (1).jpg",
      "count": 1,
      "img": "https://firebasestorage.googleapis.com/v0/b/mono-project-35634.appspot.com/o/images%2F1.-zapechenyj-mono-z-los%20(1).jpg?alt=media&token=0423f207-68b4-47d2-b498-cc41b6bb13b7"
    },
    {
      "id": "c602",
      "category": "Роли",
      "name": "Запечені моно макі з лососем",
      "path": "zapecheni-mono-maki-z-lososem",
      "description": "Рис, лосось, моно соус, унагі соус, кунжут",
      "weight": 150,
      "price": 237,
      "imagePath": "C:\\fakepath\\5.-zapecheni-mono-maki-z-krevetkoyu.jpg",
      "count": 1,
      "img": "https://firebasestorage.googleapis.com/v0/b/mono-project-35634.appspot.com/o/images%2F5.-zapecheni-mono-maki-z-krevetkoyu.jpg?alt=media&token=dde652bf-fe75-4f96-a3ea-8f30dd8fd420"
    },
    {
      "id": "f206",
      "category": "Роли",
      "name": "Запечені моно макі з креветкою",
      "path": "zapechenyj-mono-maki-z-krevetkoyu",
      "description": "Рис, креветка, моно соус, унагі соус, кунжут",
      "weight": 150,
      "price": 144,
      "imagePath": "C:\\fakepath\\1.-zapechenyj-mono-z-los (1).jpg",
      "count": 1,
      "img": "https://firebasestorage.googleapis.com/v0/b/mono-project-35634.appspot.com/o/images%2F1.-zapechenyj-mono-z-los%20(1).jpg?alt=media&token=4bd446bf-36ae-48c5-93c0-75f24169815a"
    },
    {
      "id": "f3b4",
      "category": "Роли",
      "name": "Запечені сирні макі з креветкою",
      "path": "zapechenyj-syrni-maki-z-krevetkoyu",
      "description": "Рис, креветка, сирний соус, унагі соус, кунжут",
      "weight": 150,
      "price": 254,
      "imagePath": "C:\\fakepath\\1.-zapechenyj-mono-z-los.jpg",
      "count": 1,
      "img": "https://firebasestorage.googleapis.com/v0/b/mono-project-35634.appspot.com/o/images%2F1.-zapechenyj-mono-z-los.jpg?alt=media&token=709cb301-33f5-450e-958c-10e7d84613a2"
    },
    {
      "id": "6d09",
      "category": "Роли",
      "name": "Вегетаріанський з чукою",
      "path": "vegetarianskyj-z-chukoyu",
      "description": " Рис, крем сир, авокадо, айсберг, кунжут, чука, горіховий соус, мигдаль",
      "weight": 300,
      "price": 249,
      "imagePath": "C:\\fakepath\\6.-vegetarianskyj-z-chukoyu.jpg",
      "count": 1,
      "img": "https://firebasestorage.googleapis.com/v0/b/mono-project-35634.appspot.com/o/images%2F6.-vegetarianskyj-z-chukoyu.jpg?alt=media&token=cec21b73-1b4e-48da-89d8-5d13cfd4c1ed"
    },
    {
      "id": "6c40",
      "category": "Роли",
      "name": "Сирний",
      "path": "syrnyj",
      "description": "Рис, крем сир, фета, кунжут",
      "weight": 240,
      "price": 204,
      "imagePath": "C:\\fakepath\\01.-syrnyj.jpg",
      "count": 1,
      "img": "https://firebasestorage.googleapis.com/v0/b/mono-project-35634.appspot.com/o/images%2F01.-syrnyj.jpg?alt=media&token=56684017-3cce-4886-b4ab-3c12f85c1857"
    },
    {
      "id": "6a2d",
      "category": "Роли",
      "name": "Фелікс з лососем",
      "path": "feliks-z-lososem",
      "description": "Рис, крем сир, авокадо, салат айсберг, кунжут, лосось, спайсі соус",
      "weight": 300,
      "price": 320,
      "imagePath": "C:\\fakepath\\5.-feliks-z-lososem (1).jpg",
      "count": 1,
      "img": "https://firebasestorage.googleapis.com/v0/b/mono-project-35634.appspot.com/o/images%2F5.-feliks-z-lososem%20(1).jpg?alt=media&token=8183ca44-423d-4002-a89f-bec5312b884e"
    },
    {
      "id": "b31c",
      "category": "Роли",
      "name": "Фелікс з креветкою",
      "path": "feliks-z-krevetkoyu",
      "description": "Рис, крем сир, авокадо, салат айсберг, кунжут, креветка, спайсі соус",
      "weight": 300,
      "price": 322,
      "imagePath": "C:\\fakepath\\6.-feliks-z-krevetkoyu.jpg",
      "count": 1,
      "img": "https://firebasestorage.googleapis.com/v0/b/mono-project-35634.appspot.com/o/images%2F6.-feliks-z-krevetkoyu.jpg?alt=media&token=3a960d23-acc1-4e10-9fe7-5cd259bb3ab3"
    }
  ],
  "users": [
    {
      "email": "oliynuchkaaa@gmail.com",
      "password": "123",
      "role": "ADMIN"
    },
    {
      "email": "alinaAAA@gmail.com",
      "password": "123",
      "role": "USER"
    }
  ]
}